rcoredepai_sdk/__init__.py
rcoredepai_sdk/cli.py
rcoredepai_sdk/client.py
rcoredepai_sdk/ipfs.py
rcoredepai_sdk/storage.py
rcoredepai_sdk/training.py
rcoredepai_sdk-1.0.1.dist-info/METADATA
rcoredepai_sdk-1.0.1.dist-info/WHEEL
rcoredepai_sdk-1.0.1.dist-info/entry_points.txt
rcoredepai_sdk-1.0.1.dist-info/top_level.txt
rcoredepai_sdk-1.0.1.dist-info/RECORD
