Metadata-Version: 2.4
Name: RCOREDepAI-sdk
Version: 1.0.1
Requires-Dist: web3>=6.20.0
Requires-Dist: eth-account
Requires-Dist: python-dotenv
Requires-Dist: requests
Requires-Dist: click
Requires-Dist: onnxruntime
Requires-Dist: numpy
Dynamic: requires-dist
